db_query/__init__.py
db_query/test.py
db_query-1.3.0.dist-info/DESCRIPTION.rst
db_query-1.3.0.dist-info/METADATA
db_query-1.3.0.dist-info/RECORD
db_query-1.3.0.dist-info/WHEEL
db_query-1.3.0.dist-info/metadata.json
db_query-1.3.0.dist-info/top_level.txt
