Metadata-Version: 2.0
Name: db-query
Version: 1.3.0
Summary: Module for comfortable using of databases (tested for sqlite3)
Home-page: https://github.com/Mr-Andersen/db_query
Author: Andrew Anderson
Author-email: andrew-anderson.neo@yandex.ru
License: MIT
Platform: UNKNOWN
Classifier: Programming Language :: Python :: 3
Classifier: License :: OSI Approved :: MIT License
Classifier: Operating System :: OS Independent
